baseline_checker/__init__.py
baseline_checker/core.py
baseline_checker/web_features.py
baseline_checker/config/baseline_data.json
baseline_checker/reports/__init__.py
baseline_checker/reports/report_generator.py
baseline_checker/scanner/__init__.py
baseline_checker/scanner/file_scanner.py
baseline_checker/scanner/filters.py
baseline_checker/scanner/utils.py
baseline_checker-0.1.10.dist-info/METADATA
baseline_checker-0.1.10.dist-info/WHEEL
baseline_checker-0.1.10.dist-info/entry_points.txt
baseline_checker-0.1.10.dist-info/top_level.txt
baseline_checker-0.1.10.dist-info/RECORD
