Metadata-Version: 2.4
Name: baseline-checker
Version: 0.1.10
Summary: A modern web compatibility scanner
Author-email: Veeresh Hanni <veereshhanni347@gmail.com>
License: MIT
Project-URL: Homepage, https://github.com/Veeresh-Hanni/baseline-checker
Project-URL: Repository, https://github.com/Veeresh-Hanni/baseline-checker/issues
Keywords: scanner,web-compatibility,baseline,automation
Classifier: Programming Language :: Python :: 3
Classifier: License :: OSI Approved :: MIT License
Classifier: Operating System :: OS Independent
Requires-Python: >=3.8
Requires-Dist: rich
Requires-Dist: tqdm
Requires-Dist: pandas
Requires-Dist: python-docx
Requires-Dist: reportlab
Requires-Dist: fpdf
Requires-Dist: colorama
